Workbook

Sheet Comps
A1: COMPARABLE RENTALS — DIRECT COMPARISON
A3: # | B3: Address | C3: Year | D3: Date | E3: Rent (HK$) | F3: SA (sqm) | G3: Unit Px $/sqm | H3: Unit Px $/sqft | I3: Floor | J3: Aspect | K3: AC Platform | L3: AC % | M3: Effective SA | N3: Px Index | O3: Time % | P3: Floor % | Q3: QA % | R3: SW % | S3: Age & Qual % | T3: Location % | U3: Total % | V3: Adjusted $/sqm | W3: Unrounded | X3: Remarks
A4: 1 | B4: Unit 7, 18/F, Grandtech Centre | C4: 2026 | D4: 46143 | E4: 220000 | F4: 900 | G4: =ROUND(E4/M4,0) | H4: =ROUND(G4/10.76391,0) | I4: 18/F | J4: E | K4: 0 | L4: 0 | M4: =F4+K4*L4 | N4: 366.2 | O4: =Summary!$B$6/N4-1 | P4: -0.05 | Q4: 0 | R4: -0.03 | S4: 0 | T4: 0 | U4: =SUM(O4:T4) | V4: =ROUND(W4,0) | W4: =E4/M4*(1+U4) | X4: Same building, direct evidence
A5: 2 | B5: Unit 20, 22/F, Grandtech Centre | C5: 2026 | D5: 46183 | E5: 205000 | F5: 850 | G5: =ROUND(E5/M5,0) | H5: =ROUND(G5/10.76391,0) | I5: 22/F | J5: W | K5: 0 | L5: 0 | M5: =F5+K5*L5 | N5: 360.1 | O5: =Summary!$B$6/N5-1 | P5: -0.08 | Q5: -0.02 | R5: -0.05 | S5: 0 | T5: 0 | U5: =SUM(O5:T5) | V5: =ROUND(W5,0) | W5: =E5/M5*(1+U5) | X5: Higher floor, aspect differs
A6: 3 | B6: Unit 3, 12/F, Millennium City, On Ping Street | C6: 2026 | D6: 46101 | E6: 195000 | F6: 820 | G6: =ROUND(E6/M6,0) | H6: =ROUND(G6/10.76391,0) | I6: 12/F | J6: S | K6: 0 | L6: 0 | M6: =F6+K6*L6 | N6: 355.4 | O6: =Summary!$B$6/N6-1 | P6: 0.05 | Q6: -0.03 | R6: 0 | S6: -0.02 | T6: -0.04 | U6: =SUM(O6:T6) | V6: =ROUND(W6,0) | W6: =E6/M6*(1+U6) | X6: Sibling building, lower specification
A8: QA CROSS-CHECKS
A9: WAvg adjusted unit price (SA-weighted) | E9: =SUMPRODUCT(W4:W6,F4:F6)/SUM(F4:F6)
A10: WAvg effective SA | E10: =SUMPRODUCT(M4:M6,F4:F6)/SUM(F4:F6)
A11: Sum of effective SAs | E11: =SUM(M4:M6)

Sheet Summary
A1: SUBJECT & RENTAL CONCLUSION
A3: Subject address | B3: Units 6-11 and 13, 18/F, Grandtech Centre, No. 8 On Ping Street, Shatin
A4: Valuation date | B4: 46235
A5: Valuer | B5: BMA
A6: Subject price index | B6: 366.2
A7: Subject saleable area (sqm) | B7: 935.5
A8: Subject ancillary platform (sqm) | B8: 120
A9: Subject platform weighting | B9: 0.5
A10: Subject effective SA (sqm) | B10: =B7+B8*B9
A12: ADOPTED UNIT RATE (HK$/sqm) | B12: 225
A13: MR (monthly, HK$) | B13: =ROUND(B10*B12,0)
A14: Adopted rate (HK$/sqft) | B14: =ROUND(B12/10.76391,0)
A16: Highest adjusted comparable | B16: =MAX(Comps!V4:V6)
A17: Lowest adjusted comparable | B17: =MIN(Comps!V4:V6)
A18: Spread (unrounded basis) | B18: =ROUND((MAX(Comps!W4:W6)-MIN(Comps!W4:W6))/MIN(Comps!W4:W6),3)
A20: Comparables used | B20: =COUNT(Comps!A4:A6)
A22: MR is derived from the subject's effective SA so that the adopted rate, which was itself concluded on an effective-SA basis, reproduces the comparable unit prices.

Sheet T&R
A1: TERM & REVERSION — INCOME APPROACH
A3: INITIAL TERM
A4: Initial term (years) | B4: 3
A5: Term discount rate | B5: 0.044
A6: Term rent (annual, HK$) | B6: =Summary!B13*12
A7: YP factor (term) | B7: =ROUND((1-(1+B5)^-B4)/B5,4)
A8: PV of term | B8: =ROUND(B6*B7,0)
A10: REVERSION
A11: Reversion capitalisation rate | B11: 0.049
A12: MR (monthly, from Summary) | B12: =Summary!B13
A13: Reversion rent (annual) | B13: =ROUND(B12*12,0)
A14: YP perpetuity | B14: =ROUND(1/B11,4)
A15: PV factor (n years) | B15: =ROUND(1/(1+B11)^B4,4)
A16: PV of reversion | B16: =ROUND(ROUND(B13*B14,0)*B15,0)
A18: Total capital value | B18: =B8+B16
A19: SAY (nearest $1M) | B19: =ROUND(B18/1000000,0)*1000000
A20: Capital value (HK$/sqm effective SA) | B20: =ROUND(B18/Summary!B10,0)
